{
	"modifications": [
		{
			"modification": "createEntity",
			"entity": {
				"name": "BlockPerson",
				"primary": "id",
				"primaryColumn": "id",
				"tableName": "block_person",
				"fields": {
					"id": {
						"name": "id",
						"columnName": "id",
						"nullable": false,
						"type": "Uuid",
						"columnType": "uuid"
					}
				},
				"unique": {}
			}
		},
		{
			"modification": "createEntity",
			"entity": {
				"name": "CategoryLocale",
				"primary": "id",
				"primaryColumn": "id",
				"tableName": "category_locale",
				"fields": {
					"id": {
						"name": "id",
						"columnName": "id",
						"nullable": false,
						"type": "Uuid",
						"columnType": "uuid"
					}
				},
				"unique": {}
			}
		},
		{
			"modification": "createEntity",
			"entity": {
				"name": "Category",
				"primary": "id",
				"primaryColumn": "id",
				"tableName": "category",
				"fields": {
					"id": {
						"name": "id",
						"columnName": "id",
						"nullable": false,
						"type": "Uuid",
						"columnType": "uuid"
					}
				},
				"unique": {}
			}
		},
		{
			"modification": "updateEnum",
			"enumName": "BlockType",
			"values": [
				"Heading",
				"Text",
				"Image",
				"ImageGrid",
				"Numbers",
				"Perks",
				"People",
				"Category"
			]
		},
		{
			"modification": "createColumn",
			"entityName": "BlockPerson",
			"field": {
				"name": "order",
				"columnName": "order",
				"nullable": true,
				"type": "Integer",
				"columnType": "integer"
			}
		},
		{
			"modification": "createRelation",
			"entityName": "BlockPerson",
			"owningSide": {
				"name": "person",
				"nullable": true,
				"type": "ManyHasOne",
				"target": "Person",
				"joiningColumn": {
					"columnName": "person_id",
					"onDelete": "cascade"
				}
			}
		},
		{
			"modification": "createRelation",
			"entityName": "BlockPerson",
			"owningSide": {
				"name": "Block",
				"target": "Block",
				"inversedBy": "people",
				"nullable": true,
				"type": "ManyHasOne",
				"joiningColumn": {
					"columnName": "block_id",
					"onDelete": "restrict"
				}
			},
			"inverseSide": {
				"name": "people",
				"ownedBy": "Block",
				"type": "OneHasMany",
				"target": "BlockPerson"
			}
		},
		{
			"modification": "createRelation",
			"entityName": "Block",
			"owningSide": {
				"name": "category",
				"nullable": true,
				"type": "ManyHasOne",
				"target": "Category",
				"joiningColumn": {
					"columnName": "category_id",
					"onDelete": "cascade"
				}
			}
		},
		{
			"modification": "removeField",
			"entityName": "FrontPage",
			"fieldName": "people"
		},
		{
			"modification": "createColumn",
			"entityName": "Person",
			"field": {
				"name": "showOnFrontPage",
				"columnName": "show_on_front_page",
				"nullable": false,
				"type": "Bool",
				"columnType": "boolean"
			}
		},
		{
			"modification": "removeField",
			"entityName": "Person",
			"fieldName": "frontPage"
		},
		{
			"modification": "createColumn",
			"entityName": "PersonLocale",
			"field": {
				"name": "position",
				"columnName": "position",
				"nullable": true,
				"type": "String",
				"columnType": "text"
			}
		},
		{
			"modification": "createRelation",
			"entityName": "Page",
			"owningSide": {
				"name": "category",
				"inversedBy": "pages",
				"nullable": true,
				"type": "ManyHasOne",
				"target": "Category",
				"joiningColumn": {
					"columnName": "category_id",
					"onDelete": "set null"
				}
			},
			"inverseSide": {
				"name": "pages",
				"ownedBy": "category",
				"target": "Page",
				"type": "OneHasMany"
			}
		},
		{
			"modification": "createColumn",
			"entityName": "CategoryLocale",
			"field": {
				"name": "name",
				"columnName": "name",
				"nullable": true,
				"type": "String",
				"columnType": "text"
			}
		},
		{
			"modification": "createRelation",
			"entityName": "CategoryLocale",
			"owningSide": {
				"name": "locale",
				"nullable": false,
				"type": "ManyHasOne",
				"target": "Locale",
				"joiningColumn": {
					"columnName": "locale_id",
					"onDelete": "restrict"
				}
			}
		},
		{
			"modification": "createRelation",
			"entityName": "CategoryLocale",
			"owningSide": {
				"name": "category",
				"target": "Category",
				"inversedBy": "locales",
				"nullable": false,
				"type": "ManyHasOne",
				"joiningColumn": {
					"columnName": "category_id",
					"onDelete": "cascade"
				}
			},
			"inverseSide": {
				"name": "locales",
				"ownedBy": "category",
				"type": "OneHasMany",
				"target": "CategoryLocale"
			}
		},
		{
			"modification": "createUniqueConstraint",
			"entityName": "CategoryLocale",
			"unique": {
				"fields": [
					"category",
					"locale"
				],
				"name": "unique_CategoryLocale_category_locale_7a1d47"
			}
		}
	]
}